tuduam/__init__.py
tuduam/aerodynamics.py
tuduam/data_structures.py
tuduam/mass_metrics.py
tuduam/performance.py
tuduam/propulsion.py
tuduam/sim_ctrl.py
tuduam/version.py
tuduam/structures/__init__.py
tuduam/structures/constraints.py
tuduam/structures/optimization.py
tuduam/structures/wingbox.py
tuduam-2024.15.data/data/LICENSE
tuduam-2024.15.data/data/README.md
tuduam-2024.15.dist-info/LICENSE
tuduam-2024.15.dist-info/METADATA
tuduam-2024.15.dist-info/WHEEL
tuduam-2024.15.dist-info/top_level.txt
tuduam-2024.15.dist-info/RECORD
