Metadata-Version: 2.1
Name: tuduam
Version: 2024.15
Summary: Python module related to the course on Urban Air Mobility at the faculty of Aeropsace Engineering, TU Delft
Home-page: https://github.com/saullocastro/tuduam
Author: Saullo G. P. Castro, Damien Keijzer
Author-email: S.G.P.Castro@tudelft.nl
License: 3-Clause BSD
Keywords: eVTOL design
Classifier: Development Status :: 1 - Planning
Classifier: Intended Audience :: Education
Classifier: Intended Audience :: Science/Research
Classifier: Intended Audience :: Developers
Classifier: Topic :: Scientific/Engineering
Classifier: Topic :: Scientific/Engineering :: Mathematics
Classifier: Topic :: Education
Classifier: Topic :: Software Development
Classifier: Topic :: Software Development :: Libraries :: Python Modules
Classifier: Operating System :: Microsoft :: Windows
Classifier: Operating System :: Unix
Classifier: Operating System :: POSIX :: BSD
Classifier: Programming Language :: Python :: 3.8
Classifier: Programming Language :: Python :: 3.9
Classifier: Programming Language :: Python :: 3.10
Classifier: Programming Language :: Python :: 3.11
Classifier: License :: OSI Approved :: BSD License
License-File: LICENSE
Requires-Dist: numpy
Requires-Dist: scipy
